odoo8_addon_account_fiscal_position_vat_check-8.0.0.1.2-py2.7-nspkg.pth
odoo_addons/account_fiscal_position_vat_check/__openerp__.py
odoo_addons/account_fiscal_position_vat_check/account_invoice.py
odoo_addons/account_fiscal_position_vat_check/partner.py
odoo_addons/account_fiscal_position_vat_check/account_fiscal_position_view.xml
odoo_addons/account_fiscal_position_vat_check/__init__.py
odoo_addons/account_fiscal_position_vat_check/README.rst
odoo_addons/account_fiscal_position_vat_check/i18n/ja.po
odoo_addons/account_fiscal_position_vat_check/i18n/zh_CN.po
odoo_addons/account_fiscal_position_vat_check/i18n/account_fiscal_position_vat_check.pot
odoo_addons/account_fiscal_position_vat_check/i18n/ru.po
odoo_addons/account_fiscal_position_vat_check/i18n/pt.po
odoo_addons/account_fiscal_position_vat_check/i18n/it.po
odoo_addons/account_fiscal_position_vat_check/i18n/es.po
odoo_addons/account_fiscal_position_vat_check/i18n/nl_BE.po
odoo_addons/account_fiscal_position_vat_check/i18n/ar.po
odoo_addons/account_fiscal_position_vat_check/i18n/lt.po
odoo_addons/account_fiscal_position_vat_check/i18n/ro.po
odoo_addons/account_fiscal_position_vat_check/i18n/tr.po
odoo_addons/account_fiscal_position_vat_check/i18n/mk.po
odoo_addons/account_fiscal_position_vat_check/i18n/hr.po
odoo_addons/account_fiscal_position_vat_check/i18n/bg.po
odoo_addons/account_fiscal_position_vat_check/i18n/es_EC.po
odoo_addons/account_fiscal_position_vat_check/i18n/zh_TW.po
odoo_addons/account_fiscal_position_vat_check/i18n/hu.po
odoo_addons/account_fiscal_position_vat_check/i18n/ca.po
odoo_addons/account_fiscal_position_vat_check/i18n/id.po
odoo_addons/account_fiscal_position_vat_check/i18n/es_CR.po
odoo_addons/account_fiscal_position_vat_check/i18n/sl.po
odoo_addons/account_fiscal_position_vat_check/i18n/sr@latin.po
odoo_addons/account_fiscal_position_vat_check/i18n/th.po
odoo_addons/account_fiscal_position_vat_check/i18n/cs.po
odoo8_addon_account_fiscal_position_vat_check-8.0.0.1.2.dist-info/top_level.txt
odoo8_addon_account_fiscal_position_vat_check-8.0.0.1.2.dist-info/WHEEL
odoo8_addon_account_fiscal_position_vat_check-8.0.0.1.2.dist-info/RECORD
odoo8_addon_account_fiscal_position_vat_check-8.0.0.1.2.dist-info/metadata.json
odoo8_addon_account_fiscal_position_vat_check-8.0.0.1.2.dist-info/DESCRIPTION.rst
odoo8_addon_account_fiscal_position_vat_check-8.0.0.1.2.dist-info/METADATA
odoo8_addon_account_fiscal_position_vat_check-8.0.0.1.2.dist-info/namespace_packages.txt
